LICENSE
MANIFEST.in
README.rst
setup.py
flatlibfr/__init__.py
flatlibfr/angle.py
flatlibfr/aspects.py
flatlibfr/chart.py
flatlibfr/const.py
flatlibfr/datetime.py
flatlibfr/geopos.py
flatlibfr/lists.py
flatlibfr/object.py
flatlibfr/props.py
flatlibfr/utils.py
flatlibfr.egg-info/PKG-INFO
flatlibfr.egg-info/SOURCES.txt
flatlibfr.egg-info/dependency_links.txt
flatlibfr.egg-info/requires.txt
flatlibfr.egg-info/top_level.txt
flatlibfr/dignities/__init__.py
flatlibfr/dignities/accidental.py
flatlibfr/dignities/essential.py
flatlibfr/dignities/tables.py
flatlibfr/ephem/__init__.py
flatlibfr/ephem/eph.py
flatlibfr/ephem/ephem.py
flatlibfr/ephem/swe.py
flatlibfr/ephem/tools.py
flatlibfr/predictives/__init__.py
flatlibfr/predictives/primarydirections.py
flatlibfr/predictives/profections.py
flatlibfr/predictives/returns.py
flatlibfr/protocols/__init__.py
flatlibfr/protocols/almutem.py
flatlibfr/protocols/behavior.py
flatlibfr/protocols/temperament.py
flatlibfr/resources/README.md
flatlibfr/resources/swefiles/fixstars.cat
flatlibfr/resources/swefiles/seas_12.se1
flatlibfr/resources/swefiles/seas_18.se1
flatlibfr/resources/swefiles/seas_24.se1
flatlibfr/resources/swefiles/semo_12.se1
flatlibfr/resources/swefiles/semo_18.se1
flatlibfr/resources/swefiles/semo_24.se1
flatlibfr/resources/swefiles/sepl_12.se1
flatlibfr/resources/swefiles/sepl_18.se1
flatlibfr/resources/swefiles/sepl_24.se1
flatlibfr/tools/__init__.py
flatlibfr/tools/arabicparts.py
flatlibfr/tools/chartdynamics.py
flatlibfr/tools/planetarytime.py